<?xml version = '1.0' encoding = 'UTF-8'?>
<TableProxyOraclev20c class="oracle.dbtools.crest.model.design.storage.oracle.v20c.TableProxyOraclev20c" name="OKR_ACTIVITY" directorySegmentName="seg_0" id="4FC113B9-AD68-ABFA-207E-6164920B35A0">
<createdBy>bohor</createdBy>
<createdTime>2026-05-28 18:10:03 UTC</createdTime>
<ownerDesignName>mer</ownerDesignName>
<schemaObject>29F73E7E-6ED0-6D22-A8E7-E516F10B9427</schemaObject>
<logging>YES</logging>
<partitionedRowMovement>DISABLE</partitionedRowMovement>
<segment>A10205B5-24D3-6CC3-DC2F-D790A7ED9F40</segment>
<tableSpace>A9CDD5BB-B30C-C03F-9D3A-2B16AA0E0BD7</tableSpace>
<temporaryChanged>false</temporaryChanged>
<accessDriverType>oracle_loader</accessDriverType>
<rejectLimit></rejectLimit>
<inMemory>NO</inMemory>
<columnProxies itemClass="oracle.dbtools.crest.model.design.storage.oracle.v12c.ColumnProxyOraclev12c">
<ColumnProxy name="OKR_ACTIVITY_ID" id="07AD64D2-32FC-A1C9-50C3-C0E80A1578FF">
<createdBy>bohor</createdBy>
<createdTime>2026-05-28 18:10:04 UTC</createdTime>
<ownerDesignName>mer</ownerDesignName>
</ColumnProxy>
<ColumnProxy name="UPDATED_AT" id="17D1A016-1600-E13F-F62A-B50C57200E84">
<createdBy>bohor</createdBy>
<createdTime>2026-05-28 18:10:04 UTC</createdTime>
<ownerDesignName>mer</ownerDesignName>
<defaultValue>SYSTIMESTAMP</defaultValue>
</ColumnProxy>
<ColumnProxy name="UPDATED_BY" id="2611E82D-4EF9-0E0D-E8EB-4547980A9C00">
<createdBy>bohor</createdBy>
<createdTime>2026-05-28 18:10:04 UTC</createdTime>
<ownerDesignName>mer</ownerDesignName>
</ColumnProxy>
<ColumnProxy name="DELETED_BY" id="2980A1DF-AF1F-F2D2-8E26-6CAA19A34DBA">
<createdBy>bohor</createdBy>
<createdTime>2026-05-28 18:10:04 UTC</createdTime>
<ownerDesignName>mer</ownerDesignName>
</ColumnProxy>
<ColumnProxy name="RESPONSIBLE" id="2A5AEBC8-DB80-0897-4DCA-DEDF9B526527">
<createdBy>bohor</createdBy>
<createdTime>2026-05-28 18:10:04 UTC</createdTime>
<ownerDesignName>mer</ownerDesignName>
</ColumnProxy>
<ColumnProxy name="PCT" id="3768ADF5-2CF3-AF24-8C93-2C430ADDBF12">
<createdBy>bohor</createdBy>
<createdTime>2026-05-28 18:10:04 UTC</createdTime>
<ownerDesignName>mer</ownerDesignName>
<defaultValue>0</defaultValue>
</ColumnProxy>
<ColumnProxy name="DELETED_AT" id="4A464A1F-CC37-6B37-73B2-AE7595396DEB">
<createdBy>bohor</createdBy>
<createdTime>2026-05-28 18:10:04 UTC</createdTime>
<ownerDesignName>mer</ownerDesignName>
</ColumnProxy>
<ColumnProxy name="STATUS_ID" id="77B40567-050F-90F9-6DEE-1190A01F4A57">
<createdBy>bohor</createdBy>
<createdTime>2026-05-28 18:10:04 UTC</createdTime>
<ownerDesignName>mer</ownerDesignName>
</ColumnProxy>
<ColumnProxy name="SORT_ORDER" id="96F9358C-508E-29BA-4596-0B7BEF996B94">
<createdBy>bohor</createdBy>
<createdTime>2026-05-28 18:10:04 UTC</createdTime>
<ownerDesignName>mer</ownerDesignName>
<defaultValue>0</defaultValue>
</ColumnProxy>
<ColumnProxy name="IS_DELETED" id="9A23031B-C470-FD7D-ACD7-1392B79A135B">
<createdBy>bohor</createdBy>
<createdTime>2026-05-28 18:10:04 UTC</createdTime>
<ownerDesignName>mer</ownerDesignName>
<defaultValue>&apos;N&apos;</defaultValue>
</ColumnProxy>
<ColumnProxy name="OKR_ID" id="ABB22D32-F8FD-D2E5-67E6-4652CA1A0A32">
<createdBy>bohor</createdBy>
<createdTime>2026-05-28 18:10:04 UTC</createdTime>
<ownerDesignName>mer</ownerDesignName>
</ColumnProxy>
<ColumnProxy name="CREATED_BY" id="AF9578EE-E2C8-803E-E063-238FA18A459E">
<createdBy>bohor</createdBy>
<createdTime>2026-05-28 18:10:04 UTC</createdTime>
<ownerDesignName>mer</ownerDesignName>
</ColumnProxy>
<ColumnProxy name="DELIVERABLE" id="C59F7C09-6723-C3D5-EC5C-94414E83D616">
<createdBy>bohor</createdBy>
<createdTime>2026-05-28 18:10:04 UTC</createdTime>
<ownerDesignName>mer</ownerDesignName>
</ColumnProxy>
<ColumnProxy name="LEGACY_ID" id="C9A06A0F-4D44-51FE-E5F1-603F17D59371">
<createdBy>bohor</createdBy>
<createdTime>2026-05-28 18:10:04 UTC</createdTime>
<ownerDesignName>mer</ownerDesignName>
</ColumnProxy>
<ColumnProxy name="TEXT" id="DB44586E-0169-9D04-EBC0-D63E0FA3CF12">
<createdBy>bohor</createdBy>
<createdTime>2026-05-28 18:10:04 UTC</createdTime>
<ownerDesignName>mer</ownerDesignName>
</ColumnProxy>
<ColumnProxy name="DEPENDENCY" id="E9DD5DF6-BEAF-7076-7B92-F737FB901257">
<createdBy>bohor</createdBy>
<createdTime>2026-05-28 18:10:04 UTC</createdTime>
<ownerDesignName>mer</ownerDesignName>
</ColumnProxy>
<ColumnProxy name="CREATED_AT" id="EB645A0A-FBBE-B7DB-5CD6-DD9F84373CBB">
<createdBy>bohor</createdBy>
<createdTime>2026-05-28 18:10:04 UTC</createdTime>
<ownerDesignName>mer</ownerDesignName>
<defaultValue>SYSTIMESTAMP</defaultValue>
</ColumnProxy>
</columnProxies>
<indexProxies>
<IndexProxy class="oracle.dbtools.crest.model.design.storage.oracle.v10g.IndexProxyOraclev10g" name="IX_OKR_ACTIVITY__OKR" id="59F2AE40-400D-4495-2905-154DE83BE631">
<createdBy>bohor</createdBy>
<createdTime>2026-05-28 18:10:08 UTC</createdTime>
<ownerDesignName>mer</ownerDesignName>
<schemaObject>29F73E7E-6ED0-6D22-A8E7-E516F10B9427</schemaObject>
<segment>16C73C0A-478A-4DAD-61E5-F3A0B4061226</segment>
<tableSpace>A9CDD5BB-B30C-C03F-9D3A-2B16AA0E0BD7</tableSpace>
</IndexProxy>
<IndexProxy class="oracle.dbtools.crest.model.design.storage.oracle.v10g.IndexProxyOraclev10g" name="PK_OKR_ACTIVITY" id="62FEDA99-8995-FF62-9CB2-9655FCA98DC8">
<createdBy>bohor</createdBy>
<createdTime>2026-05-28 18:10:08 UTC</createdTime>
<ownerDesignName>mer</ownerDesignName>
<schemaObject>29F73E7E-6ED0-6D22-A8E7-E516F10B9427</schemaObject>
<segment>16C73C0A-478A-4DAD-61E5-F3A0B4061226</segment>
<tableSpace>A9CDD5BB-B30C-C03F-9D3A-2B16AA0E0BD7</tableSpace>
</IndexProxy>
<IndexProxy class="oracle.dbtools.crest.model.design.storage.oracle.v10g.IndexProxyOraclev10g" name="IX_OKR_ACTIVITY__STATUS" id="730758BC-EC73-C952-2AB4-24AD7114BFEA">
<createdBy>bohor</createdBy>
<createdTime>2026-05-28 18:10:08 UTC</createdTime>
<ownerDesignName>mer</ownerDesignName>
<schemaObject>29F73E7E-6ED0-6D22-A8E7-E516F10B9427</schemaObject>
<segment>16C73C0A-478A-4DAD-61E5-F3A0B4061226</segment>
<tableSpace>A9CDD5BB-B30C-C03F-9D3A-2B16AA0E0BD7</tableSpace>
</IndexProxy>
<IndexProxy class="oracle.dbtools.crest.model.design.storage.oracle.v10g.IndexProxyOraclev10g" name="UK_OKR_ACTIVITY__OKR_LEGACY" id="B8C5148A-40E0-981A-6B0E-490239992F5C">
<createdBy>bohor</createdBy>
<createdTime>2026-05-28 18:10:08 UTC</createdTime>
<ownerDesignName>mer</ownerDesignName>
<schemaObject>29F73E7E-6ED0-6D22-A8E7-E516F10B9427</schemaObject>
<segment>16C73C0A-478A-4DAD-61E5-F3A0B4061226</segment>
<tableSpace>A9CDD5BB-B30C-C03F-9D3A-2B16AA0E0BD7</tableSpace>
</IndexProxy>
</indexProxies>
<foreignKeys>
<ForeignKey class="oracle.dbtools.crest.model.design.storage.oracle.v10g.FKProxyOraclev10g" name="FK_OKR_ACTIVITY__OKR" id="3589833A-41BC-7614-0F34-41954D7F2B1E">
<createdBy>bohor</createdBy>
<createdTime>2026-05-28 18:10:17 UTC</createdTime>
<ownerDesignName>mer</ownerDesignName>
</ForeignKey>
<ForeignKey class="oracle.dbtools.crest.model.design.storage.oracle.v10g.FKProxyOraclev10g" name="FK_OKR_ACTIVITY__STATUS" id="6207F331-26D8-17EA-9C23-BFBF61A782B3">
<createdBy>bohor</createdBy>
<createdTime>2026-05-28 18:10:17 UTC</createdTime>
<ownerDesignName>mer</ownerDesignName>
</ForeignKey>
</foreignKeys>
<lobStorages>
<LobStorage class="oracle.dbtools.crest.model.design.storage.oracle.v11g.LobStorageOraclev11g" name="SYS_LOB0000077261C00006$$" id="AADE7634-74F4-FAB0-A887-5E424DD09A36">
<createdBy>bohor</createdBy>
<createdTime>2026-05-28 18:10:17 UTC</createdTime>
<ownerDesignName>mer</ownerDesignName>
<cache>NOCACHE</cache>
<chunk>8192</chunk>
<column>TEXT</column>
<compression>NO</compression>
<duplication>KEEP_DUPLICATES</duplication>
<logging>YES</logging>
<tableSpace>A9CDD5BB-B30C-C03F-9D3A-2B16AA0E0BD7</tableSpace>
<lobStorageType>SECUREFILE</lobStorageType>
</LobStorage>
<LobStorage class="oracle.dbtools.crest.model.design.storage.oracle.v11g.LobStorageOraclev11g" name="SYS_LOB0000077261C00009$$" id="DC150EF8-958E-15C9-8594-0D41AFF3B7F9">
<createdBy>bohor</createdBy>
<createdTime>2026-05-28 18:10:17 UTC</createdTime>
<ownerDesignName>mer</ownerDesignName>
<cache>NOCACHE</cache>
<chunk>8192</chunk>
<column>DELIVERABLE</column>
<compression>NO</compression>
<duplication>KEEP_DUPLICATES</duplication>
<logging>YES</logging>
<tableSpace>A9CDD5BB-B30C-C03F-9D3A-2B16AA0E0BD7</tableSpace>
<lobStorageType>SECUREFILE</lobStorageType>
</LobStorage>
</lobStorages>
<primaryKeys>
<PrimaryKey class="oracle.dbtools.crest.model.design.storage.oracle.v10g.PKProxyOraclev10g" name="PK_OKR_ACTIVITY" id="30AE39CA-52D5-DD36-9111-113995698AB0">
<createdBy>bohor</createdBy>
<createdTime>2026-05-28 18:10:12 UTC</createdTime>
<ownerDesignName>mer</ownerDesignName>
<segment>16C73C0A-478A-4DAD-61E5-F3A0B4061226</segment>
<tableSpace>A9CDD5BB-B30C-C03F-9D3A-2B16AA0E0BD7</tableSpace>
<existingIndex>62FEDA99-8995-FF62-9CB2-9655FCA98DC8</existingIndex>
<indexSegment>16C73C0A-478A-4DAD-61E5-F3A0B4061226</indexSegment>
<indexSort>SORTED</indexSort>
<usingIndex>BY INDEX NAME</usingIndex>
</PrimaryKey>
</primaryKeys>
<uniqueKeys>
<UniqueKey class="oracle.dbtools.crest.model.design.storage.oracle.v10g.UniqueOraclev10g" name="UK_OKR_ACTIVITY__OKR_LEGACY" id="2FD0A025-0CDD-5193-FA1F-6AB8C35971D2">
<createdBy>bohor</createdBy>
<createdTime>2026-05-28 18:10:12 UTC</createdTime>
<ownerDesignName>mer</ownerDesignName>
<segment>16C73C0A-478A-4DAD-61E5-F3A0B4061226</segment>
<tableSpace>A9CDD5BB-B30C-C03F-9D3A-2B16AA0E0BD7</tableSpace>
<existingIndex>B8C5148A-40E0-981A-6B0E-490239992F5C</existingIndex>
<indexSegment>16C73C0A-478A-4DAD-61E5-F3A0B4061226</indexSegment>
<indexSort>SORTED</indexSort>
<usingIndex>BY INDEX NAME</usingIndex>
</UniqueKey>
</uniqueKeys>
</TableProxyOraclev20c>